asyncllm/__init__.py
asyncllm/ollama/__init__.py
asyncllm/ollama/deepseek.cpython-312-x86_64-linux-gnu.so
asyncllm/ollama/requests/deepseek.cpython-312-x86_64-linux-gnu.so
asyncllm/openai/__init__.py
asyncllm/openai/deepseek.cpython-312-x86_64-linux-gnu.so
asyncllm/openai/openrouter/deepseek.cpython-312-x86_64-linux-gnu.so
asyncllm/openai/requests/deepseek.cpython-312-x86_64-linux-gnu.so
asyncllm-0.0.0.1.dist-info/LICENSE
asyncllm-0.0.0.1.dist-info/METADATA
asyncllm-0.0.0.1.dist-info/WHEEL
asyncllm-0.0.0.1.dist-info/top_level.txt
asyncllm-0.0.0.1.dist-info/zip-safe
asyncllm-0.0.0.1.dist-info/RECORD
